[
  {
    "Item ID": "1",
    "Name": "Iron Pickaxe",
    "Rarity": "0",
    "Use Time": "20 (Very fast)",
    "Velocity": "",
    "Tool Speed": "13",
    "Pickaxe Power": "40%",
    "Hammer Power": "0%",
    "Axe Power": "0%",
    "Fishing Power": "",
    "Recipes": []
  },
  {
    "Item ID": "7",
    "Name": "Iron Hammer",
    "Rarity": "0",
    "Use Time": "30 (Average)",
    "Velocity": "",
    "Tool Speed": "20",
    "Pickaxe Power": "0%",
    "Hammer Power": "40%",
    "Axe Power": "0%",
    "Fishing Power": "",
    "Recipes": []
  },
  {
    "Item ID": "10",
    "Name": "Iron Axe",
    "Rarity": "0",
    "Use Time": "27 (Average)",
    "Velocity": "",
    "Tool Speed": "19",
    "Pickaxe Power": "0%",
    "Hammer Power": "0%",
    "Axe Power": "45%",
    "Fishing Power": "",
    "Recipes": []
  },
  {
    "Item ID": "45",
    "Name": "War Axe of the Night",
    "Rarity": "1",
    "Use Time": "30 (Average)",
    "Velocity": "",
    "Tool Speed": "15",
    "Pickaxe Power": "0%",
    "Hammer Power": "0%",
    "Axe Power": "75%",
    "Fishing Power": "",
    "Recipes": []
  },
  {
    "Item ID": "50",
    "Name": "Magic Mirror",
    "Rarity": "1",
    "Use Time": "90 (Snail)",
    "Velocity": "",
    "Tool Speed": "",
    "Pickaxe Power": "",
    "Hammer Power": "",
    "Axe Power": "",
    "Fishing Power": "",
    "Recipes": []
  },
  {
    "Item ID": "103",
    "Name": "Nightmare Pickaxe",
    "Rarity": "1",
    "Use Time": "20 (Very fast)",
    "Velocity": "",
    "Tool Speed": "15",
    "Pickaxe Power": "65%",
    "Hammer Power": "0%",
    "Axe Power": "0%",
    "Fishing Power": "",
    "Recipes": []
  },
  {
    "Item ID": "104",
    "Name": "The Breaker",
    "Rarity": "1",
    "Use Time": "45 (Very slow)",
    "Velocity": "",
    "Tool Speed": "19",
    "Pickaxe Power": "0%",
    "Hammer Power": "55%",
    "Axe Power": "0%",
    "Fishing Power": "",
    "Recipes": []
  },
  {
    "Item ID": "122",
    "Name": "Molten Pickaxe",
    "Rarity": "3",
    "Use Time": "23 (Fast)",
    "Velocity": "",
    "Tool Speed": "18",
    "Pickaxe Power": "100%",
    "Hammer Power": "0%",
    "Axe Power": "0%",
    "Fishing Power": "",
    "Recipes": []
  },
  {
    "Item ID": "196",
    "Name": "Wooden Hammer",
    "Rarity": "0",
    "Use Time": "37 (Very slow)",
    "Velocity": "",
    "Tool Speed": "25",
    "Pickaxe Power": "0%",
    "Hammer Power": "25%",
    "Axe Power": "0%",
    "Fishing Power": "",
    "Recipes": []
  },
  {
    "Item ID": "204",
    "Name": "Meteor Hamaxe",
    "Rarity": "1",
    "Use Time": "30 (Average)",
    "Velocity": "",
    "Tool Speed": "16",
    "Pickaxe Power": "0%",
    "Hammer Power": "60%",
    "Axe Power": "100%",
    "Fishing Power": "",
    "Recipes": []
  },
  {
    "Item ID": "205",
    "Name": "Empty Bucket",
    "Rarity": "0",
    "Use Time": "10 (Very fast)",
    "Velocity": "",
    "Tool Speed": "",
    "Pickaxe Power": "",
    "Hammer Power": "",
    "Axe Power": "",
    "Fishing Power": "",
    "Recipes": []
  },
  {
    "Item ID": "206",
    "Name": "Water Bucket",
    "Rarity": "0",
    "Use Time": "10 (Very fast)",
    "Velocity": "",
    "Tool Speed": "",
    "Pickaxe Power": "",
    "Hammer Power": "",
    "Axe Power": "",
    "Fishing Power": "",
    "Recipes": []
  },
  {
    "Item ID": "207",
    "Name": "Lava Bucket",
    "Rarity": "0",
    "Use Time": "10 (Very fast)",
    "Velocity": "",
    "Tool Speed": "",
    "Pickaxe Power": "",
    "Hammer Power": "",
    "Axe Power": "",
    "Fishing Power": "",
    "Recipes": []
  },
  {
    "Item ID": "213",
    "Name": "Staff of Regrowth",
    "Rarity": "3",
    "Use Time": "25 (Fast)",
    "Velocity": "",
    "Tool Speed": "",
    "Pickaxe Power": "",
    "Hammer Power": "",
    "Axe Power": "",
    "Fishing Power": "",
    "Recipes": []
  },
  {
    "Item ID": "217",
    "Name": "Molten Hamaxe",
    "Rarity": "3",
    "Use Time": "27 (Average)",
    "Velocity": "",
    "Tool Speed": "14",
    "Pickaxe Power": "0%",
    "Hammer Power": "70%",
    "Axe Power": "150%",
    "Fishing Power": "",
    "Recipes": []
  },
  {
    "Item ID": "367",
    "Name": "Pwnhammer",
    "Rarity": "4",
    "Use Time": "27 (Average)",
    "Velocity": "",
    "Tool Speed": "14",
    "Pickaxe Power": "0%",
    "Hammer Power": "80%",
    "Axe Power": "0%",
    "Fishing Power": "",
    "Recipes": []
  },
  {
    "Item ID": "383",
    "Name": "Cobalt Chainsaw",
    "Rarity": "4",
    "Use Time": "15 (Very fast)",
    "Velocity": "",
    "Tool Speed": "7",
    "Pickaxe Power": "0%",
    "Hammer Power": "0%",
    "Axe Power": "70%",
    "Fishing Power": "",
    "Recipes": []
  },
  {
    "Item ID": "384",
    "Name": "Mythril Chainsaw",
    "Rarity": "4",
    "Use Time": "15 (Very fast)",
    "Velocity": "",
    "Tool Speed": "6",
    "Pickaxe Power": "0%",
    "Hammer Power": "0%",
    "Axe Power": "85%",
    "Fishing Power": "",
    "Recipes": []
  },
  {
    "Item ID": "385",
    "Name": "Cobalt Drill",
    "Rarity": "4",
    "Use Time": "15 (Very fast)",
    "Velocity": "",
    "Tool Speed": "7",
    "Pickaxe Power": "110%",
    "Hammer Power": "0%",
    "Axe Power": "0%",
    "Fishing Power": "",
    "Recipes": []
  },
  {
    "Item ID": "386",
    "Name": "Mythril Drill",
    "Rarity": "4",
    "Use Time": "15 (Very fast)",
    "Velocity": "",
    "Tool Speed": "6",
    "Pickaxe Power": "150%",
    "Hammer Power": "0%",
    "Axe Power": "0%",
    "Fishing Power": "",
    "Recipes": []
  },
  {
    "Item ID": "387",
    "Name": "Adamantite Chainsaw",
    "Rarity": "4",
    "Use Time": "15 (Very fast)",
    "Velocity": "",
    "Tool Speed": "4",
    "Pickaxe Power": "0%",
    "Hammer Power": "0%",
    "Axe Power": "100%",
    "Fishing Power": "",
    "Recipes": []
  },
  {
    "Item ID": "388",
    "Name": "Adamantite Drill",
    "Rarity": "4",
    "Use Time": "15 (Very fast)",
    "Velocity": "",
    "Tool Speed": "4",
    "Pickaxe Power": "180%",
    "Hammer Power": "0%",
    "Axe Power": "0%",
    "Fishing Power": "",
    "Recipes": []
  },
  {
    "Item ID": "509",
    "Name": "Red Wrench",
    "Rarity": "1",
    "Use Time": "15 (Very fast)",
    "Velocity": "",
    "Tool Speed": "",
    "Pickaxe Power": "",
    "Hammer Power": "",
    "Axe Power": "",
    "Fishing Power": "",
    "Recipes": []
  },
  {
    "Item ID": "510",
    "Name": "Wire Cutter",
    "Rarity": "1",
    "Use Time": "15 (Very fast)",
    "Velocity": "",
    "Tool Speed": "",
    "Pickaxe Power": "",
    "Hammer Power": "",
    "Axe Power": "",
    "Fishing Power": "",
    "Recipes": []
  },
  {
    "Item ID": "579",
    "Name": "Drax",
    "Rarity": "4",
    "Use Time": "15 (Very fast)",
    "Velocity": "",
    "Tool Speed": "4",
    "Pickaxe Power": "200%",
    "Hammer Power": "0%",
    "Axe Power": "110%",
    "Fishing Power": "",
    "Recipes": []
  },
  {
    "Item ID": "654",
    "Name": "Ebonwood Hammer",
    "Rarity": "0",
    "Use Time": "30 (Average)",
    "Velocity": "",
    "Tool Speed": "20",
    "Pickaxe Power": "0%",
    "Hammer Power": "40%",
    "Axe Power": "0%",
    "Fishing Power": "",
    "Recipes": []
  },
  {
    "Item ID": "657",
    "Name": "Rich Mahogany Hammer",
    "Rarity": "0",
    "Use Time": "33 (Slow)",
    "Velocity": "",
    "Tool Speed": "23",
    "Pickaxe Power": "0%",
    "Hammer Power": "35%",
    "Axe Power": "0%",
    "Fishing Power": "",
    "Recipes": []
  },
  {
    "Item ID": "660",
    "Name": "Pearlwood Hammer",
    "Rarity": "0",
    "Use Time": "29 (Average)",
    "Velocity": "",
    "Tool Speed": "19",
    "Pickaxe Power": "0%",
    "Hammer Power": "45%",
    "Axe Power": "0%",
    "Fishing Power": "",
    "Recipes": []
  },
  {
    "Item ID": "776",
    "Name": "Cobalt Pickaxe",
    "Rarity": "4",
    "Use Time": "25 (Fast)",
    "Velocity": "",
    "Tool Speed": "13",
    "Pickaxe Power": "110%",
    "Hammer Power": "0%",
    "Axe Power": "0%",
    "Fishing Power": "",
    "Recipes": []
  },
  {
    "Item ID": "777",
    "Name": "Mythril Pickaxe",
    "Rarity": "4",
    "Use Time": "25 (Fast)",
    "Velocity": "",
    "Tool Speed": "10",
    "Pickaxe Power": "150%",
    "Hammer Power": "0%",
    "Axe Power": "0%",
    "Fishing Power": "",
    "Recipes": []
  },
  {
    "Item ID": "778",
    "Name": "Adamantite Pickaxe",
    "Rarity": "4",
    "Use Time": "25 (Fast)",
    "Velocity": "",
    "Tool Speed": "8",
    "Pickaxe Power": "180%",
    "Hammer Power": "0%",
    "Axe Power": "0%",
    "Fishing Power": "",
    "Recipes": []
  },
  {
    "Item ID": "779",
    "Name": "Clentaminator",
    "Rarity": "5",
    "Use Time": "30 (Average)",
    "Velocity": "",
    "Tool Speed": "",
    "Pickaxe Power": "",
    "Hammer Power": "",
    "Axe Power": "",
    "Fishing Power": "",
    "Recipes": []
  },
  {
    "Item ID": "787",
    "Name": "Hammush",
    "Rarity": "7",
    "Use Time": "27 (Average)",
    "Velocity": "",
    "Tool Speed": "14",
    "Pickaxe Power": "0%",
    "Hammer Power": "85%",
    "Axe Power": "0%",
    "Fishing Power": "",
    "Recipes": []
  },
  {
    "Item ID": "797",
    "Name": "Flesh Grinder",
    "Rarity": "1",
    "Use Time": "40 (Very slow)",
    "Velocity": "",
    "Tool Speed": "19",
    "Pickaxe Power": "0%",
    "Hammer Power": "55%",
    "Axe Power": "0%",
    "Fishing Power": "",
    "Recipes": []
  },
  {
    "Item ID": "798",
    "Name": "Deathbringer Pickaxe",
    "Rarity": "1",
    "Use Time": "22 (Fast)",
    "Velocity": "",
    "Tool Speed": "14",
    "Pickaxe Power": "70%",
    "Hammer Power": "0%",
    "Axe Power": "0%",
    "Fishing Power": "",
    "Recipes": []
  },
  {
    "Item ID": "799",
    "Name": "Blood Lust Cluster",
    "Rarity": "1",
    "Use Time": "32 (Slow)",
    "Velocity": "",
    "Tool Speed": "15",
    "Pickaxe Power": "0%",
    "Hammer Power": "0%",
    "Axe Power": "75%",
    "Fishing Power": "",
    "Recipes": []
  },
  {
    "Item ID": "832",
    "Name": "Living Wood Wand",
    "Rarity": "1",
    "Use Time": "15 (Very fast)",
    "Velocity": "",
    "Tool Speed": "",
    "Pickaxe Power": "",
    "Hammer Power": "",
    "Axe Power": "",
    "Fishing Power": "",
    "Recipes": []
  },
  {
    "Item ID": "850",
    "Name": "Blue Wrench",
    "Rarity": "1",
    "Use Time": "15 (Very fast)",
    "Velocity": "",
    "Tool Speed": "",
    "Pickaxe Power": "",
    "Hammer Power": "",
    "Axe Power": "",
    "Fishing Power": "",
    "Recipes": []
  },
  {
    "Item ID": "851",
    "Name": "Green Wrench",
    "Rarity": "1",
    "Use Time": "15 (Very fast)",
    "Velocity": "",
    "Tool Speed": "",
    "Pickaxe Power": "",
    "Hammer Power": "",
    "Axe Power": "",
    "Fishing Power": "",
    "Recipes": []
  },
  {
    "Item ID": "882",
    "Name": "Cactus Pickaxe",
    "Rarity": "0",
    "Use Time": "25 (Fast)",
    "Velocity": "",
    "Tool Speed": "16",
    "Pickaxe Power": "35%",
    "Hammer Power": "0%",
    "Axe Power": "0%",
    "Fishing Power": "",
    "Recipes": []
  },
  {
    "Item ID": "922",
    "Name": "Shadewood Hammer",
    "Rarity": "0",
    "Use Time": "30 (Average)",
    "Velocity": "",
    "Tool Speed": "20",
    "Pickaxe Power": "0%",
    "Hammer Power": "40%",
    "Axe Power": "0%",
    "Fishing Power": "",
    "Recipes": []
  },
  {
    "Item ID": "932",
    "Name": "Bone Wand",
    "Rarity": "1",
    "Use Time": "15 (Very fast)",
    "Velocity": "",
    "Tool Speed": "",
    "Pickaxe Power": "",
    "Hammer Power": "",
    "Axe Power": "",
    "Fishing Power": "",
    "Recipes": []
  },
  {
    "Item ID": "933",
    "Name": "Leaf Wand",
    "Rarity": "1",
    "Use Time": "15 (Very fast)",
    "Velocity": "",
    "Tool Speed": "",
    "Pickaxe Power": "",
    "Hammer Power": "",
    "Axe Power": "",
    "Fishing Power": "",
    "Recipes": []
  },
  {
    "Item ID": "946",
    "Name": "Umbrella",
    "Rarity": "1",
    "Use Time": "22 (Fast)",
    "Velocity": "",
    "Tool Speed": "",
    "Pickaxe Power": "",
    "Hammer Power": "",
    "Axe Power": "",
    "Fishing Power": "",
    "Recipes": []
  },
  {
    "Item ID": "990",
    "Name": "Pickaxe Axe",
    "Rarity": "4",
    "Use Time": "25 (Fast)",
    "Velocity": "",
    "Tool Speed": "7",
    "Pickaxe Power": "200%",
    "Hammer Power": "0%",
    "Axe Power": "110%",
    "Fishing Power": "",
    "Recipes": []
  },
  {
    "Item ID": "991",
    "Name": "Cobalt Waraxe",
    "Rarity": "4",
    "Use Time": "35 (Slow)",
    "Velocity": "",
    "Tool Speed": "13",
    "Pickaxe Power": "0%",
    "Hammer Power": "0%",
    "Axe Power": "70%",
    "Fishing Power": "",
    "Recipes": []
  },
  {
    "Item ID": "992",
    "Name": "Mythril Waraxe",
    "Rarity": "4",
    "Use Time": "35 (Slow)",
    "Velocity": "",
    "Tool Speed": "10",
    "Pickaxe Power": "0%",
    "Hammer Power": "0%",
    "Axe Power": "85%",
    "Fishing Power": "",
    "Recipes": []
  },
  {
    "Item ID": "993",
    "Name": "Adamantite Waraxe",
    "Rarity": "4",
    "Use Time": "35 (Slow)",
    "Velocity": "",
    "Tool Speed": "8",
    "Pickaxe Power": "0%",
    "Hammer Power": "0%",
    "Axe Power": "100%",
    "Fishing Power": "",
    "Recipes": []
  },
  {
    "Item ID": "1071",
    "Name": "Paintbrush",
    "Rarity": "0",
    "Use Time": "15 (Very fast)",
    "Velocity": "",
    "Tool Speed": "",
    "Pickaxe Power": "",
    "Hammer Power": "",
    "Axe Power": "",
    "Fishing Power": "",
    "Recipes": []
  },
  {
    "Item ID": "1072",
    "Name": "Paint Roller",
    "Rarity": "0",
    "Use Time": "15 (Very fast)",
    "Velocity": "",
    "Tool Speed": "",
    "Pickaxe Power": "",
    "Hammer Power": "",
    "Axe Power": "",
    "Fishing Power": "",
    "Recipes": []
  },
  {
    "Item ID": "1100",
    "Name": "Paint Scraper",
    "Rarity": "0",
    "Use Time": "15 (Very fast)",
    "Velocity": "",
    "Tool Speed": "",
    "Pickaxe Power": "",
    "Hammer Power": "",
    "Axe Power": "",
    "Fishing Power": "",
    "Recipes": []
  },
  {
    "Item ID": "1128",
    "Name": "Honey Bucket",
    "Rarity": "0",
    "Use Time": "10 (Very fast)",
    "Velocity": "",
    "Tool Speed": "",
    "Pickaxe Power": "",
    "Hammer Power": "",
    "Axe Power": "",
    "Fishing Power": "",
    "Recipes": []
  },
  {
    "Item ID": "1129",
    "Name": "Hive Wand",
    "Rarity": "1",
    "Use Time": "15 (Very fast)",
    "Velocity": "",
    "Tool Speed": "",
    "Pickaxe Power": "",
    "Hammer Power": "",
    "Axe Power": "",
    "Fishing Power": "",
    "Recipes": []
  },
  {
    "Item ID": "1188",
    "Name": "Palladium Pickaxe",
    "Rarity": "4",
    "Use Time": "25 (Fast)",
    "Velocity": "",
    "Tool Speed": "12",
    "Pickaxe Power": "130%",
    "Hammer Power": "0%",
    "Axe Power": "0%",
    "Fishing Power": "",
    "Recipes": []
  },
  {
    "Item ID": "1189",
    "Name": "Palladium Drill",
    "Rarity": "4",
    "Use Time": "15 (Very fast)",
    "Velocity": "",
    "Tool Speed": "7",
    "Pickaxe Power": "130%",
    "Hammer Power": "0%",
    "Axe Power": "0%",
    "Fishing Power": "",
    "Recipes": []
  },
  {
    "Item ID": "1190",
    "Name": "Palladium Chainsaw",
    "Rarity": "4",
    "Use Time": "15 (Very fast)",
    "Velocity": "",
    "Tool Speed": "7",
    "Pickaxe Power": "0%",
    "Hammer Power": "0%",
    "Axe Power": "75%",
    "Fishing Power": "",
    "Recipes": []
  },
  {
    "Item ID": "1195",
    "Name": "Orichalcum Pickaxe",
    "Rarity": "4",
    "Use Time": "25 (Fast)",
    "Velocity": "",
    "Tool Speed": "9",
    "Pickaxe Power": "165%",
    "Hammer Power": "0%",
    "Axe Power": "0%",
    "Fishing Power": "",
    "Recipes": []
  },
  {
    "Item ID": "1196",
    "Name": "Orichalcum Drill",
    "Rarity": "4",
    "Use Time": "15 (Very fast)",
    "Velocity": "",
    "Tool Speed": "5",
    "Pickaxe Power": "165%",
    "Hammer Power": "0%",
    "Axe Power": "0%",
    "Fishing Power": "",
    "Recipes": []
  },
  {
    "Item ID": "1197",
    "Name": "Orichalcum Chainsaw",
    "Rarity": "4",
    "Use Time": "15 (Very fast)",
    "Velocity": "",
    "Tool Speed": "5",
    "Pickaxe Power": "0%",
    "Hammer Power": "0%",
    "Axe Power": "90%",
    "Fishing Power": "",
    "Recipes": []
  },
  {
    "Item ID": "1202",
    "Name": "Titanium Pickaxe",
    "Rarity": "4",
    "Use Time": "25 (Fast)",
    "Velocity": "",
    "Tool Speed": "7",
    "Pickaxe Power": "190%",
    "Hammer Power": "0%",
    "Axe Power": "0%",
    "Fishing Power": "",
    "Recipes": []
  },
  {
    "Item ID": "1203",
    "Name": "Titanium Drill",
    "Rarity": "4",
    "Use Time": "15 (Very fast)",
    "Velocity": "",
    "Tool Speed": "4",
    "Pickaxe Power": "190%",
    "Hammer Power": "0%",
    "Axe Power": "0%",
    "Fishing Power": "",
    "Recipes": []
  },
  {
    "Item ID": "1204",
    "Name": "Titanium Chainsaw",
    "Rarity": "4",
    "Use Time": "15 (Very fast)",
    "Velocity": "",
    "Tool Speed": "4",
    "Pickaxe Power": "0%",
    "Hammer Power": "0%",
    "Axe Power": "105%",
    "Fishing Power": "",
    "Recipes": []
  },
  {
    "Item ID": "1222",
    "Name": "Palladium Waraxe",
    "Rarity": "4",
    "Use Time": "35 (Slow)",
    "Velocity": "",
    "Tool Speed": "12",
    "Pickaxe Power": "0%",
    "Hammer Power": "0%",
    "Axe Power": "75%",
    "Fishing Power": "",
    "Recipes": []
  },
  {
    "Item ID": "1223",
    "Name": "Orichalcum Waraxe",
    "Rarity": "4",
    "Use Time": "35 (Slow)",
    "Velocity": "",
    "Tool Speed": "9",
    "Pickaxe Power": "0%",
    "Hammer Power": "0%",
    "Axe Power": "90%",
    "Fishing Power": "",
    "Recipes": []
  },
  {
    "Item ID": "1224",
    "Name": "Titanium Waraxe",
    "Rarity": "4",
    "Use Time": "35 (Slow)",
    "Velocity": "",
    "Tool Speed": "7",
    "Pickaxe Power": "0%",
    "Hammer Power": "0%",
    "Axe Power": "105%",
    "Fishing Power": "",
    "Recipes": []
  },
  {
    "Item ID": "1230",
    "Name": "Chlorophyte Pickaxe",
    "Rarity": "7",
    "Use Time": "25 (Fast)",
    "Velocity": "",
    "Tool Speed": "7",
    "Pickaxe Power": "200%",
    "Hammer Power": "0%",
    "Axe Power": "0%",
    "Fishing Power": "",
    "Recipes": []
  },
  {
    "Item ID": "1231",
    "Name": "Chlorophyte Drill",
    "Rarity": "7",
    "Use Time": "15 (Very fast)",
    "Velocity": "",
    "Tool Speed": "4",
    "Pickaxe Power": "200%",
    "Hammer Power": "0%",
    "Axe Power": "0%",
    "Fishing Power": "",
    "Recipes": []
  },
  {
    "Item ID": "1232",
    "Name": "Chlorophyte Chainsaw",
    "Rarity": "7",
    "Use Time": "15 (Very fast)",
    "Velocity": "",
    "Tool Speed": "4",
    "Pickaxe Power": "0%",
    "Hammer Power": "0%",
    "Axe Power": "115%",
    "Fishing Power": "",
    "Recipes": []
  },
  {
    "Item ID": "1233",
    "Name": "Chlorophyte Greataxe",
    "Rarity": "7",
    "Use Time": "30 (Average)",
    "Velocity": "",
    "Tool Speed": "7",
    "Pickaxe Power": "0%",
    "Hammer Power": "0%",
    "Axe Power": "115%",
    "Fishing Power": "",
    "Recipes": []
  },
  {
    "Item ID": "1234",
    "Name": "Chlorophyte Warhammer",
    "Rarity": "7",
    "Use Time": "35 (Slow)",
    "Velocity": "",
    "Tool Speed": "14",
    "Pickaxe Power": "0%",
    "Hammer Power": "90%",
    "Axe Power": "0%",
    "Fishing Power": "",
    "Recipes": []
  },
  {
    "Item ID": "1262",
    "Name": "Chlorophyte Jackhammer",
    "Rarity": "7",
    "Use Time": "25 (Fast)",
    "Velocity": "",
    "Tool Speed": "7",
    "Pickaxe Power": "0%",
    "Hammer Power": "90%",
    "Axe Power": "0%",
    "Fishing Power": "",
    "Recipes": []
  },
  {
    "Item ID": "1294",
    "Name": "Picksaw",
    "Rarity": "7",
    "Use Time": "16 (Very fast)",
    "Velocity": "",
    "Tool Speed": "6",
    "Pickaxe Power": "210%",
    "Hammer Power": "0%",
    "Axe Power": "125%",
    "Fishing Power": "",
    "Recipes": []
  },
  {
    "Item ID": "1305",
    "Name": "The Axe",
    "Rarity": "8",
    "Use Time": "23 (Fast)",
    "Velocity": "",
    "Tool Speed": "7",
    "Pickaxe Power": "0%",
    "Hammer Power": "100%",
    "Axe Power": "175%",
    "Fishing Power": "",
    "Recipes": []
  },
  {
    "Item ID": "1320",
    "Name": "Bone Pickaxe",
    "Rarity": "1",
    "Use Time": "19 (Very fast)",
    "Velocity": "",
    "Tool Speed": "11",
    "Pickaxe Power": "55%",
    "Hammer Power": "0%",
    "Axe Power": "0%",
    "Fishing Power": "",
    "Recipes": []
  },
  {
    "Item ID": "1326",
    "Name": "Rod of Discord",
    "Rarity": "7",
    "Use Time": "20 (Very fast)",
    "Velocity": "",
    "Tool Speed": "",
    "Pickaxe Power": "",
    "Hammer Power": "",
    "Axe Power": "",
    "Fishing Power": "",
    "Recipes": []
  },
  {
    "Item ID": "1506",
    "Name": "Spectre Pickaxe",
    "Rarity": "8",
    "Use Time": "24 (Fast)",
    "Velocity": "",
    "Tool Speed": "10",
    "Pickaxe Power": "200%",
    "Hammer Power": "0%",
    "Axe Power": "0%",
    "Fishing Power": "",
    "Recipes": []
  },
  {
    "Item ID": "1507",
    "Name": "Spectre Hamaxe",
    "Rarity": "8",
    "Use Time": "28 (Average)",
    "Velocity": "",
    "Tool Speed": "8",
    "Pickaxe Power": "0%",
    "Hammer Power": "90%",
    "Axe Power": "150%",
    "Fishing Power": "",
    "Recipes": []
  },
  {
    "Item ID": "1543",
    "Name": "Spectre Paintbrush",
    "Rarity": "0",
    "Use Time": "15 (Very fast)",
    "Velocity": "",
    "Tool Speed": "",
    "Pickaxe Power": "",
    "Hammer Power": "",
    "Axe Power": "",
    "Fishing Power": "",
    "Recipes": []
  },
  {
    "Item ID": "1544",
    "Name": "Spectre Paint Roller",
    "Rarity": "0",
    "Use Time": "15 (Very fast)",
    "Velocity": "",
    "Tool Speed": "",
    "Pickaxe Power": "",
    "Hammer Power": "",
    "Axe Power": "",
    "Fishing Power": "",
    "Recipes": []
  },
  {
    "Item ID": "1545",
    "Name": "Spectre Paint Scraper",
    "Rarity": "0",
    "Use Time": "15 (Very fast)",
    "Velocity": "",
    "Tool Speed": "",
    "Pickaxe Power": "",
    "Hammer Power": "",
    "Axe Power": "",
    "Fishing Power": "",
    "Recipes": []
  },
  {
    "Item ID": "1786",
    "Name": "Sickle",
    "Rarity": "0",
    "Use Time": "24 (Fast)",
    "Velocity": "",
    "Tool Speed": "",
    "Pickaxe Power": "",
    "Hammer Power": "",
    "Axe Power": "",
    "Fishing Power": "",
    "Recipes": []
  },
  {
    "Item ID": "1917",
    "Name": "Candy Cane Pickaxe",
    "Rarity": "0",
    "Use Time": "20 (Very fast)",
    "Velocity": "",
    "Tool Speed": "16",
    "Pickaxe Power": "55%",
    "Hammer Power": "0%",
    "Axe Power": "0%",
    "Fishing Power": "",
    "Recipes": []
  },
  {
    "Item ID": "1991",
    "Name": "Bug Net",
    "Rarity": "0",
    "Use Time": "25 (Fast)",
    "Velocity": "",
    "Tool Speed": "",
    "Pickaxe Power": "",
    "Hammer Power": "",
    "Axe Power": "",
    "Fishing Power": "",
    "Recipes": []
  },
  {
    "Item ID": "2176",
    "Name": "Shroomite Digging Claw",
    "Rarity": "8",
    "Use Time": "12 (Very fast)",
    "Velocity": "",
    "Tool Speed": "4",
    "Pickaxe Power": "200%",
    "Hammer Power": "0%",
    "Axe Power": "125%",
    "Fishing Power": "",
    "Recipes": []
  },
  {
    "Item ID": "2289",
    "Name": "Wood Fishing Pole",
    "Rarity": "0",
    "Use Time": "8 (Insanely fast)",
    "Velocity": "9",
    "Tool Speed": "",
    "Pickaxe Power": "",
    "Hammer Power": "",
    "Axe Power": "",
    "Fishing Power": "5%",
    "Recipes": []
  },
  {
    "Item ID": "2291",
    "Name": "Reinforced Fishing Pole",
    "Rarity": "0",
    "Use Time": "8 (Insanely fast)",
    "Velocity": "11",
    "Tool Speed": "",
    "Pickaxe Power": "",
    "Hammer Power": "",
    "Axe Power": "",
    "Fishing Power": "15%",
    "Recipes": []
  },
  {
    "Item ID": "2292",
    "Name": "Fiberglass Fishing Pole",
    "Rarity": "2",
    "Use Time": "8 (Insanely fast)",
    "Velocity": "14",
    "Tool Speed": "",
    "Pickaxe Power": "",
    "Hammer Power": "",
    "Axe Power": "",
    "Fishing Power": "30%",
    "Recipes": []
  },
  {
    "Item ID": "2293",
    "Name": "Fisher of Souls",
    "Rarity": "1",
    "Use Time": "8 (Insanely fast)",
    "Velocity": "13",
    "Tool Speed": "",
    "Pickaxe Power": "",
    "Hammer Power": "",
    "Axe Power": "",
    "Fishing Power": "20%",
    "Recipes": []
  },
  {
    "Item ID": "2294",
    "Name": "Golden Fishing Rod",
    "Rarity": "3",
    "Use Time": "8 (Insanely fast)",
    "Velocity": "17",
    "Tool Speed": "",
    "Pickaxe Power": "",
    "Hammer Power": "",
    "Axe Power": "",
    "Fishing Power": "50%",
    "Recipes": []
  },
  {
    "Item ID": "2295",
    "Name": "Mechanic's Rod",
    "Rarity": "2",
    "Use Time": "8 (Insanely fast)",
    "Velocity": "15",
    "Tool Speed": "",
    "Pickaxe Power": "",
    "Hammer Power": "",
    "Axe Power": "",
    "Fishing Power": "35%",
    "Recipes": []
  },
  {
    "Item ID": "2296",
    "Name": "Sitting Duck's Fishing Pole",
    "Rarity": "2",
    "Use Time": "8 (Insanely fast)",
    "Velocity": "16",
    "Tool Speed": "",
    "Pickaxe Power": "",
    "Hammer Power": "",
    "Axe Power": "",
    "Fishing Power": "40%",
    "Recipes": []
  },
  {
    "Item ID": "2320",
    "Name": "Rockfish",
    "Rarity": "3",
    "Use Time": "24 (Fast)",
    "Velocity": "",
    "Tool Speed": "14",
    "Pickaxe Power": "0%",
    "Hammer Power": "70%",
    "Axe Power": "0%",
    "Fishing Power": "",
    "Recipes": []
  },
  {
    "Item ID": "2341",
    "Name": "Reaver Shark",
    "Rarity": "3",
    "Use Time": "22 (Fast)",
    "Velocity": "",
    "Tool Speed": "13",
    "Pickaxe Power": "59%",
    "Hammer Power": "0%",
    "Axe Power": "0%",
    "Fishing Power": "",
    "Recipes": []
  },
  {
    "Item ID": "2342",
    "Name": "Sawtooth Shark",
    "Rarity": "3",
    "Use Time": "15 (Very fast)",
    "Velocity": "",
    "Tool Speed": "4",
    "Pickaxe Power": "0%",
    "Hammer Power": "0%",
    "Axe Power": "70%",
    "Fishing Power": "",
    "Recipes": []
  },
  {
    "Item ID": "2421",
    "Name": "Fleshcatcher",
    "Rarity": "1",
    "Use Time": "8 (Insanely fast)",
    "Velocity": "13.5",
    "Tool Speed": "",
    "Pickaxe Power": "",
    "Hammer Power": "",
    "Axe Power": "",
    "Fishing Power": "22%",
    "Recipes": []
  },
  {
    "Item ID": "2422",
    "Name": "Hotline Fishing Hook",
    "Rarity": "3",
    "Use Time": "8 (Insanely fast)",
    "Velocity": "16.5",
    "Tool Speed": "",
    "Pickaxe Power": "",
    "Hammer Power": "",
    "Axe Power": "",
    "Fishing Power": "45%",
    "Recipes": []
  },
  {
    "Item ID": "2516",
    "Name": "Palm Wood Hammer",
    "Rarity": "0",
    "Use Time": "33 (Slow)",
    "Velocity": "",
    "Tool Speed": "23",
    "Pickaxe Power": "0%",
    "Hammer Power": "35%",
    "Axe Power": "0%",
    "Fishing Power": "",
    "Recipes": []
  },
  {
    "Item ID": "2746",
    "Name": "Boreal Wood Hammer",
    "Rarity": "0",
    "Use Time": "33 (Slow)",
    "Velocity": "",
    "Tool Speed": "23",
    "Pickaxe Power": "0%",
    "Hammer Power": "35%",
    "Axe Power": "0%",
    "Fishing Power": "",
    "Recipes": []
  },
  {
    "Item ID": "2772",
    "Name": "Vortex Axe",
    "Rarity": "0",
    "Use Time": "25 (Fast)",
    "Velocity": "",
    "Tool Speed": "7",
    "Pickaxe Power": "0%",
    "Hammer Power": "0%",
    "Axe Power": "135%",
    "Fishing Power": "",
    "Recipes": []
  },
  {
    "Item ID": "2773",
    "Name": "Vortex Chainsaw",
    "Rarity": "0",
    "Use Time": "15 (Very fast)",
    "Velocity": "",
    "Tool Speed": "4",
    "Pickaxe Power": "0%",
    "Hammer Power": "0%",
    "Axe Power": "135%",
    "Fishing Power": "",
    "Recipes": []
  },
  {
    "Item ID": "2774",
    "Name": "Vortex Drill",
    "Rarity": "0",
    "Use Time": "15 (Very fast)",
    "Velocity": "",
    "Tool Speed": "2",
    "Pickaxe Power": "225%",
    "Hammer Power": "0%",
    "Axe Power": "0%",
    "Fishing Power": "",
    "Recipes": []
  },
  {
    "Item ID": "2775",
    "Name": "Vortex Hammer",
    "Rarity": "0",
    "Use Time": "30 (Average)",
    "Velocity": "",
    "Tool Speed": "7",
    "Pickaxe Power": "0%",
    "Hammer Power": "100%",
    "Axe Power": "0%",
    "Fishing Power": "",
    "Recipes": []
  },
  {
    "Item ID": "2776",
    "Name": "Vortex Pickaxe",
    "Rarity": "0",
    "Use Time": "12 (Very fast)",
    "Velocity": "",
    "Tool Speed": "6",
    "Pickaxe Power": "225%",
    "Hammer Power": "0%",
    "Axe Power": "0%",
    "Fishing Power": "",
    "Recipes": []
  },
  {
    "Item ID": "2777",
    "Name": "Nebula Axe",
    "Rarity": "0",
    "Use Time": "25 (Fast)",
    "Velocity": "",
    "Tool Speed": "7",
    "Pickaxe Power": "0%",
    "Hammer Power": "0%",
    "Axe Power": "135%",
    "Fishing Power": "",
    "Recipes": []
  },
  {
    "Item ID": "2778",
    "Name": "Nebula Chainsaw",
    "Rarity": "0",
    "Use Time": "15 (Very fast)",
    "Velocity": "",
    "Tool Speed": "4",
    "Pickaxe Power": "0%",
    "Hammer Power": "0%",
    "Axe Power": "135%",
    "Fishing Power": "",
    "Recipes": []
  },
  {
    "Item ID": "2779",
    "Name": "Nebula Drill",
    "Rarity": "0",
    "Use Time": "15 (Very fast)",
    "Velocity": "",
    "Tool Speed": "2",
    "Pickaxe Power": "225%",
    "Hammer Power": "0%",
    "Axe Power": "0%",
    "Fishing Power": "",
    "Recipes": []
  },
  {
    "Item ID": "2780",
    "Name": "Nebula Hammer",
    "Rarity": "0",
    "Use Time": "30 (Average)",
    "Velocity": "",
    "Tool Speed": "7",
    "Pickaxe Power": "0%",
    "Hammer Power": "100%",
    "Axe Power": "0%",
    "Fishing Power": "",
    "Recipes": []
  },
  {
    "Item ID": "2781",
    "Name": "Nebula Pickaxe",
    "Rarity": "0",
    "Use Time": "12 (Very fast)",
    "Velocity": "",
    "Tool Speed": "6",
    "Pickaxe Power": "225%",
    "Hammer Power": "0%",
    "Axe Power": "0%",
    "Fishing Power": "",
    "Recipes": []
  },
  {
    "Item ID": "2782",
    "Name": "Solar Flare Axe",
    "Rarity": "0",
    "Use Time": "25 (Fast)",
    "Velocity": "",
    "Tool Speed": "7",
    "Pickaxe Power": "0%",
    "Hammer Power": "0%",
    "Axe Power": "135%",
    "Fishing Power": "",
    "Recipes": []
  },
  {
    "Item ID": "2783",
    "Name": "Solar Flare Chainsaw",
    "Rarity": "0",
    "Use Time": "15 (Very fast)",
    "Velocity": "",
    "Tool Speed": "4",
    "Pickaxe Power": "0%",
    "Hammer Power": "0%",
    "Axe Power": "135%",
    "Fishing Power": "",
    "Recipes": []
  },
  {
    "Item ID": "2784",
    "Name": "Solar Flare Drill",
    "Rarity": "0",
    "Use Time": "15 (Very fast)",
    "Velocity": "",
    "Tool Speed": "2",
    "Pickaxe Power": "225%",
    "Hammer Power": "0%",
    "Axe Power": "0%",
    "Fishing Power": "",
    "Recipes": []
  },
  {
    "Item ID": "2785",
    "Name": "Solar Flare Hammer",
    "Rarity": "0",
    "Use Time": "30 (Average)",
    "Velocity": "",
    "Tool Speed": "7",
    "Pickaxe Power": "0%",
    "Hammer Power": "100%",
    "Axe Power": "0%",
    "Fishing Power": "",
    "Recipes": []
  },
  {
    "Item ID": "2786",
    "Name": "Solar Flare Pickaxe",
    "Rarity": "0",
    "Use Time": "12 (Very fast)",
    "Velocity": "",
    "Tool Speed": "6",
    "Pickaxe Power": "225%",
    "Hammer Power": "0%",
    "Axe Power": "0%",
    "Fishing Power": "",
    "Recipes": []
  },
  {
    "Item ID": "2798",
    "Name": "Laser Drill",
    "Rarity": "8",
    "Use Time": "25 (Fast)",
    "Velocity": "",
    "Tool Speed": "6",
    "Pickaxe Power": "230%",
    "Hammer Power": "0%",
    "Axe Power": "150%",
    "Fishing Power": "",
    "Recipes": []
  },
  {
    "Item ID": "3031",
    "Name": "Bottomless Water Bucket",
    "Rarity": "7",
    "Use Time": "12 (Very fast)",
    "Velocity": "",
    "Tool Speed": "",
    "Pickaxe Power": "",
    "Hammer Power": "",
    "Axe Power": "",
    "Fishing Power": "",
    "Recipes": []
  },
  {
    "Item ID": "3032",
    "Name": "Super Absorbant Sponge",
    "Rarity": "7",
    "Use Time": "12 (Very fast)",
    "Velocity": "",
    "Tool Speed": "",
    "Pickaxe Power": "",
    "Hammer Power": "",
    "Axe Power": "",
    "Fishing Power": "",
    "Recipes": []
  },
  {
    "Item ID": "3098",
    "Name": "Butcher's Chainsaw",
    "Rarity": "8",
    "Use Time": "15 (Very fast)",
    "Velocity": "",
    "Tool Speed": "4",
    "Pickaxe Power": "0%",
    "Hammer Power": "0%",
    "Axe Power": "150%",
    "Fishing Power": "",
    "Recipes": []
  },
  {
    "Item ID": "3124",
    "Name": "Cell Phone",
    "Rarity": "7",
    "Use Time": "90 (Snail)",
    "Velocity": "",
    "Tool Speed": "",
    "Pickaxe Power": "",
    "Hammer Power": "",
    "Axe Power": "",
    "Fishing Power": "",
    "Recipes": []
  },
  {
    "Item ID": "3182",
    "Name": "Magic Water Dropper",
    "Rarity": "0",
    "Use Time": "10 (Very fast)",
    "Velocity": "",
    "Tool Speed": "",
    "Pickaxe Power": "",
    "Hammer Power": "",
    "Axe Power": "",
    "Fishing Power": "",
    "Recipes": []
  },
  {
    "Item ID": "3183",
    "Name": "Golden Bug Net",
    "Rarity": "4",
    "Use Time": "18 (Very fast)",
    "Velocity": "",
    "Tool Speed": "",
    "Pickaxe Power": "",
    "Hammer Power": "",
    "Axe Power": "",
    "Fishing Power": "",
    "Recipes": []
  },
  {
    "Item ID": "3184",
    "Name": "Magic Lava Dropper",
    "Rarity": "0",
    "Use Time": "10 (Very fast)",
    "Velocity": "",
    "Tool Speed": "",
    "Pickaxe Power": "",
    "Hammer Power": "",
    "Axe Power": "",
    "Fishing Power": "",
    "Recipes": []
  },
  {
    "Item ID": "3185",
    "Name": "Magic Honey Dropper",
    "Rarity": "0",
    "Use Time": "10 (Very fast)",
    "Velocity": "",
    "Tool Speed": "",
    "Pickaxe Power": "",
    "Hammer Power": "",
    "Axe Power": "",
    "Fishing Power": "",
    "Recipes": []
  },
  {
    "Item ID": "3199",
    "Name": "Ice Mirror",
    "Rarity": "1",
    "Use Time": "90 (Snail)",
    "Velocity": "",
    "Tool Speed": "",
    "Pickaxe Power": "",
    "Hammer Power": "",
    "Axe Power": "",
    "Fishing Power": "",
    "Recipes": []
  },
  {
    "Item ID": "3360",
    "Name": "Living Mahogany Wand",
    "Rarity": "1",
    "Use Time": "15 (Very fast)",
    "Velocity": "",
    "Tool Speed": "",
    "Pickaxe Power": "",
    "Hammer Power": "",
    "Axe Power": "",
    "Fishing Power": "",
    "Recipes": []
  },
  {
    "Item ID": "3361",
    "Name": "Rich Mahogany Leaf Wand",
    "Rarity": "1",
    "Use Time": "15 (Very fast)",
    "Velocity": "",
    "Tool Speed": "",
    "Pickaxe Power": "",
    "Hammer Power": "",
    "Axe Power": "",
    "Fishing Power": "",
    "Recipes": []
  },
  {
    "Item ID": "3384",
    "Name": "Portal Gun",
    "Rarity": "8",
    "Use Time": "20 (Very fast)",
    "Velocity": "",
    "Tool Speed": "",
    "Pickaxe Power": "",
    "Hammer Power": "",
    "Axe Power": "",
    "Fishing Power": "",
    "Recipes": []
  },
  {
    "Item ID": "3462",
    "Name": "Stardust Axe",
    "Rarity": "0",
    "Use Time": "25 (Fast)",
    "Velocity": "",
    "Tool Speed": "7",
    "Pickaxe Power": "0%",
    "Hammer Power": "0%",
    "Axe Power": "135%",
    "Fishing Power": "",
    "Recipes": []
  },
  {
    "Item ID": "3463",
    "Name": "Stardust Chainsaw",
    "Rarity": "0",
    "Use Time": "15 (Very fast)",
    "Velocity": "",
    "Tool Speed": "4",
    "Pickaxe Power": "0%",
    "Hammer Power": "0%",
    "Axe Power": "135%",
    "Fishing Power": "",
    "Recipes": []
  },
  {
    "Item ID": "3464",
    "Name": "Stardust Drill",
    "Rarity": "0",
    "Use Time": "15 (Very fast)",
    "Velocity": "",
    "Tool Speed": "2",
    "Pickaxe Power": "225%",
    "Hammer Power": "0%",
    "Axe Power": "0%",
    "Fishing Power": "",
    "Recipes": []
  },
  {
    "Item ID": "3465",
    "Name": "Stardust Hammer",
    "Rarity": "0",
    "Use Time": "30 (Average)",
    "Velocity": "",
    "Tool Speed": "7",
    "Pickaxe Power": "0%",
    "Hammer Power": "100%",
    "Axe Power": "0%",
    "Fishing Power": "",
    "Recipes": []
  },
  {
    "Item ID": "3466",
    "Name": "Stardust Pickaxe",
    "Rarity": "0",
    "Use Time": "12 (Very fast)",
    "Velocity": "",
    "Tool Speed": "6",
    "Pickaxe Power": "225%",
    "Hammer Power": "0%",
    "Axe Power": "0%",
    "Fishing Power": "",
    "Recipes": []
  },
  {
    "Item ID": "3481",
    "Name": "Platinum Hammer",
    "Rarity": "0",
    "Use Time": "27 (Average)",
    "Velocity": "",
    "Tool Speed": "21",
    "Pickaxe Power": "0%",
    "Hammer Power": "59%",
    "Axe Power": "0%",
    "Fishing Power": "",
    "Recipes": []
  },
  {
    "Item ID": "3482",
    "Name": "Platinum Axe",
    "Rarity": "0",
    "Use Time": "25 (Fast)",
    "Velocity": "",
    "Tool Speed": "17",
    "Pickaxe Power": "0%",
    "Hammer Power": "0%",
    "Axe Power": "60%",
    "Fishing Power": "",
    "Recipes": []
  },
  {
    "Item ID": "3485",
    "Name": "Platinum Pickaxe",
    "Rarity": "0",
    "Use Time": "19 (Very fast)",
    "Velocity": "",
    "Tool Speed": "15",
    "Pickaxe Power": "59%",
    "Hammer Power": "0%",
    "Axe Power": "0%",
    "Fishing Power": "",
    "Recipes": []
  },
  {
    "Item ID": "3487",
    "Name": "Tungsten Hammer",
    "Rarity": "0",
    "Use Time": "28 (Average)",
    "Velocity": "",
    "Tool Speed": "25",
    "Pickaxe Power": "0%",
    "Hammer Power": "50%",
    "Axe Power": "0%",
    "Fishing Power": "",
    "Recipes": []
  },
  {
    "Item ID": "3488",
    "Name": "Tungsten Axe",
    "Rarity": "0",
    "Use Time": "26 (Average)",
    "Velocity": "",
    "Tool Speed": "18",
    "Pickaxe Power": "0%",
    "Hammer Power": "0%",
    "Axe Power": "55%",
    "Fishing Power": "",
    "Recipes": []
  },
  {
    "Item ID": "3491",
    "Name": "Tungsten Pickaxe",
    "Rarity": "0",
    "Use Time": "21 (Fast)",
    "Velocity": "",
    "Tool Speed": "19",
    "Pickaxe Power": "50%",
    "Hammer Power": "0%",
    "Axe Power": "0%",
    "Fishing Power": "",
    "Recipes": []
  },
  {
    "Item ID": "3493",
    "Name": "Lead Hammer",
    "Rarity": "0",
    "Use Time": "29 (Average)",
    "Velocity": "",
    "Tool Speed": "19",
    "Pickaxe Power": "0%",
    "Hammer Power": "43%",
    "Axe Power": "0%",
    "Fishing Power": "",
    "Recipes": []
  },
  {
    "Item ID": "3494",
    "Name": "Lead Axe",
    "Rarity": "0",
    "Use Time": "28 (Average)",
    "Velocity": "",
    "Tool Speed": "19",
    "Pickaxe Power": "0%",
    "Hammer Power": "0%",
    "Axe Power": "50%",
    "Fishing Power": "",
    "Recipes": []
  },
  {
    "Item ID": "3497",
    "Name": "Lead Pickaxe",
    "Rarity": "0",
    "Use Time": "19 (Very fast)",
    "Velocity": "",
    "Tool Speed": "12",
    "Pickaxe Power": "43%",
    "Hammer Power": "0%",
    "Axe Power": "0%",
    "Fishing Power": "",
    "Recipes": []
  },
  {
    "Item ID": "3499",
    "Name": "Tin Hammer",
    "Rarity": "0",
    "Use Time": "31 (Slow)",
    "Velocity": "",
    "Tool Speed": "21",
    "Pickaxe Power": "0%",
    "Hammer Power": "38%",
    "Axe Power": "0%",
    "Fishing Power": "",
    "Recipes": []
  },
  {
    "Item ID": "3500",
    "Name": "Tin Axe",
    "Rarity": "0",
    "Use Time": "28 (Average)",
    "Velocity": "",
    "Tool Speed": "20",
    "Pickaxe Power": "0%",
    "Hammer Power": "0%",
    "Axe Power": "40%",
    "Fishing Power": "",
    "Recipes": []
  },
  {
    "Item ID": "3503",
    "Name": "Tin Pickaxe",
    "Rarity": "0",
    "Use Time": "21 (Fast)",
    "Velocity": "",
    "Tool Speed": "14",
    "Pickaxe Power": "35%",
    "Hammer Power": "0%",
    "Axe Power": "0%",
    "Fishing Power": "",
    "Recipes": []
  },
  {
    "Item ID": "3505",
    "Name": "Copper Hammer",
    "Rarity": "0",
    "Use Time": "33 (Slow)",
    "Velocity": "",
    "Tool Speed": "23",
    "Pickaxe Power": "0%",
    "Hammer Power": "35%",
    "Axe Power": "0%",
    "Fishing Power": "",
    "Recipes": []
  },
  {
    "Item ID": "3506",
    "Name": "Copper Axe",
    "Rarity": "0",
    "Use Time": "30 (Average)",
    "Velocity": "",
    "Tool Speed": "21",
    "Pickaxe Power": "0%",
    "Hammer Power": "0%",
    "Axe Power": "35%",
    "Fishing Power": "",
    "Recipes": []
  },
  {
    "Item ID": "3509",
    "Name": "Copper Pickaxe",
    "Rarity": "0",
    "Use Time": "23 (Fast)",
    "Velocity": "",
    "Tool Speed": "15",
    "Pickaxe Power": "35%",
    "Hammer Power": "0%",
    "Axe Power": "0%",
    "Fishing Power": "",
    "Recipes": []
  },
  {
    "Item ID": "3511",
    "Name": "Silver Hammer",
    "Rarity": "0",
    "Use Time": "29 (Average)",
    "Velocity": "",
    "Tool Speed": "19",
    "Pickaxe Power": "0%",
    "Hammer Power": "45%",
    "Axe Power": "0%",
    "Fishing Power": "",
    "Recipes": []
  },
  {
    "Item ID": "3512",
    "Name": "Silver Axe",
    "Rarity": "0",
    "Use Time": "26 (Average)",
    "Velocity": "",
    "Tool Speed": "18",
    "Pickaxe Power": "0%",
    "Hammer Power": "0%",
    "Axe Power": "50%",
    "Fishing Power": "",
    "Recipes": []
  },
  {
    "Item ID": "3515",
    "Name": "Silver Pickaxe",
    "Rarity": "0",
    "Use Time": "19 (Very fast)",
    "Velocity": "",
    "Tool Speed": "11",
    "Pickaxe Power": "45%",
    "Hammer Power": "0%",
    "Axe Power": "0%",
    "Fishing Power": "",
    "Recipes": []
  },
  {
    "Item ID": "3517",
    "Name": "Gold Hammer",
    "Rarity": "0",
    "Use Time": "28 (Average)",
    "Velocity": "",
    "Tool Speed": "23",
    "Pickaxe Power": "0%",
    "Hammer Power": "55%",
    "Axe Power": "0%",
    "Fishing Power": "",
    "Recipes": []
  },
  {
    "Item ID": "3518",
    "Name": "Gold Axe",
    "Rarity": "0",
    "Use Time": "26 (Average)",
    "Velocity": "",
    "Tool Speed": "18",
    "Pickaxe Power": "0%",
    "Hammer Power": "0%",
    "Axe Power": "55%",
    "Fishing Power": "",
    "Recipes": []
  },
  {
    "Item ID": "3521",
    "Name": "Gold Pickaxe",
    "Rarity": "0",
    "Use Time": "20 (Very fast)",
    "Velocity": "",
    "Tool Speed": "17",
    "Pickaxe Power": "55%",
    "Hammer Power": "0%",
    "Axe Power": "0%",
    "Fishing Power": "",
    "Recipes": []
  },
  {
    "Item ID": "3522",
    "Name": "Solar Flare Hamaxe",
    "Rarity": "0",
    "Use Time": "28 (Average)",
    "Velocity": "",
    "Tool Speed": "7",
    "Pickaxe Power": "0%",
    "Hammer Power": "100%",
    "Axe Power": "150%",
    "Fishing Power": "",
    "Recipes": []
  },
  {
    "Item ID": "3523",
    "Name": "Vortex Hamaxe",
    "Rarity": "0",
    "Use Time": "28 (Average)",
    "Velocity": "",
    "Tool Speed": "7",
    "Pickaxe Power": "0%",
    "Hammer Power": "100%",
    "Axe Power": "150%",
    "Fishing Power": "",
    "Recipes": []
  },
  {
    "Item ID": "3524",
    "Name": "Nebula Hamaxe",
    "Rarity": "0",
    "Use Time": "28 (Average)",
    "Velocity": "",
    "Tool Speed": "7",
    "Pickaxe Power": "0%",
    "Hammer Power": "100%",
    "Axe Power": "150%",
    "Fishing Power": "",
    "Recipes": []
  },
  {
    "Item ID": "3525",
    "Name": "Stardust Hamaxe",
    "Rarity": "0",
    "Use Time": "28 (Average)",
    "Velocity": "",
    "Tool Speed": "7",
    "Pickaxe Power": "0%",
    "Hammer Power": "100%",
    "Axe Power": "150%",
    "Fishing Power": "",
    "Recipes": []
  },
  {
    "Item ID": "3611",
    "Name": "The Grand Design",
    "Rarity": "2",
    "Use Time": "10 (Very fast)",
    "Velocity": "",
    "Tool Speed": "",
    "Pickaxe Power": "",
    "Hammer Power": "",
    "Axe Power": "",
    "Fishing Power": "",
    "Recipes": []
  },
  {
    "Item ID": "3612",
    "Name": "Yellow Wrench",
    "Rarity": "1",
    "Use Time": "15 (Very fast)",
    "Velocity": "",
    "Tool Speed": "",
    "Pickaxe Power": "",
    "Hammer Power": "",
    "Axe Power": "",
    "Fishing Power": "",
    "Recipes": []
  },
  {
    "Item ID": "3620",
    "Name": "Actuation Rod",
    "Rarity": "1",
    "Use Time": "15 (Very fast)",
    "Velocity": "",
    "Tool Speed": "",
    "Pickaxe Power": "",
    "Hammer Power": "",
    "Axe Power": "",
    "Fishing Power": "",
    "Recipes": []
  },
  {
    "Item ID": "3625",
    "Name": "Multicolor Wrench",
    "Rarity": "1",
    "Use Time": "15 (Very fast)",
    "Velocity": "",
    "Tool Speed": "",
    "Pickaxe Power": "",
    "Hammer Power": "",
    "Axe Power": "",
    "Fishing Power": "",
    "Recipes": []
  },
  {
    "Item ID": "3782",
    "Name": "Magic Sand Dropper",
    "Rarity": "0",
    "Use Time": "10 (Very fast)",
    "Velocity": "",
    "Tool Speed": "",
    "Pickaxe Power": "",
    "Hammer Power": "",
    "Axe Power": "",
    "Fishing Power": "",
    "Recipes": []
  },
  {
    "Item ID": "4039",
    "Name": "Golf Club (Iron)",
    "Rarity": "",
    "Use Time": "12 (Very fast)",
    "Velocity": "",
    "Tool Speed": "",
    "Pickaxe Power": "",
    "Hammer Power": "",
    "Axe Power": "",
    "Fishing Power": "",
    "Recipes": []
  },
  {
    "Item ID": "4049",
    "Name": "Lawn Mower",
    "Rarity": "1",
    "Use Time": "30 (Average)",
    "Velocity": "",
    "Tool Speed": "",
    "Pickaxe Power": "",
    "Hammer Power": "",
    "Axe Power": "",
    "Fishing Power": "",
    "Recipes": []
  },
  {
    "Item ID": "4057",
    "Name": "Rain Song",
    "Rarity": "3",
    "Use Time": "12 (Very fast)",
    "Velocity": "",
    "Tool Speed": "",
    "Pickaxe Power": "",
    "Hammer Power": "",
    "Axe Power": "",
    "Fishing Power": "",
    "Recipes": []
  },
  {
    "Item ID": "4059",
    "Name": "Fossil Pickaxe",
    "Rarity": "1",
    "Use Time": "18 (Very fast)",
    "Velocity": "",
    "Tool Speed": "14",
    "Pickaxe Power": "55%",
    "Hammer Power": "0%",
    "Axe Power": "0%",
    "Fishing Power": "",
    "Recipes": []
  },
  {
    "Item ID": "4092",
    "Name": "Golf Club (Putter)",
    "Rarity": "",
    "Use Time": "12 (Very fast)",
    "Velocity": "",
    "Tool Speed": "",
    "Pickaxe Power": "",
    "Hammer Power": "",
    "Axe Power": "",
    "Fishing Power": "",
    "Recipes": []
  },
  {
    "Item ID": "4093",
    "Name": "Golf Club (Wedge)",
    "Rarity": "",
    "Use Time": "12 (Very fast)",
    "Velocity": "",
    "Tool Speed": "",
    "Pickaxe Power": "",
    "Hammer Power": "",
    "Axe Power": "",
    "Fishing Power": "",
    "Recipes": []
  },
  {
    "Item ID": "4094",
    "Name": "Golf Club (Driver)",
    "Rarity": "",
    "Use Time": "12 (Very fast)",
    "Velocity": "",
    "Tool Speed": "",
    "Pickaxe Power": "",
    "Hammer Power": "",
    "Axe Power": "",
    "Fishing Power": "",
    "Recipes": []
  },
  {
    "Item ID": "4095",
    "Name": "Golf Whistle",
    "Rarity": "4",
    "Use Time": "10 (Very fast)",
    "Velocity": "",
    "Tool Speed": "",
    "Pickaxe Power": "",
    "Hammer Power": "",
    "Axe Power": "",
    "Fishing Power": "",
    "Recipes": []
  },
  {
    "Item ID": "4262",
    "Name": "Snake Charmer's Flute",
    "Rarity": "1",
    "Use Time": "90 (Snail)",
    "Velocity": "",
    "Tool Speed": "",
    "Pickaxe Power": "",
    "Hammer Power": "",
    "Axe Power": "",
    "Fishing Power": "",
    "Recipes": []
  },
  {
    "Item ID": "4263",
    "Name": "Magic Conch",
    "Rarity": "1",
    "Use Time": "90 (Snail)",
    "Velocity": "",
    "Tool Speed": "",
    "Pickaxe Power": "",
    "Hammer Power": "",
    "Axe Power": "",
    "Fishing Power": "",
    "Recipes": []
  },
  {
    "Item ID": "4317",
    "Name": "Haemorrhaxe",
    "Rarity": "4",
    "Use Time": "27 (Average)",
    "Velocity": "",
    "Tool Speed": "11",
    "Pickaxe Power": "0%",
    "Hammer Power": "80%",
    "Axe Power": "150%",
    "Fishing Power": "",
    "Recipes": []
  },
  {
    "Item ID": "4325",
    "Name": "Chum Caster",
    "Rarity": "2",
    "Use Time": "8 (Insanely fast)",
    "Velocity": "15",
    "Tool Speed": "",
    "Pickaxe Power": "",
    "Hammer Power": "",
    "Axe Power": "",
    "Fishing Power": "25%",
    "Recipes": []
  },
  {
    "Item ID": "4346",
    "Name": "Encumbering Stone",
    "Rarity": "1",
    "Use Time": "",
    "Velocity": "",
    "Tool Speed": "",
    "Pickaxe Power": "",
    "Hammer Power": "",
    "Axe Power": "",
    "Fishing Power": "",
    "Recipes": []
  },
  {
    "Item ID": "4372",
    "Name": "Ivy",
    "Rarity": "3",
    "Use Time": "12 (Very fast)",
    "Velocity": "",
    "Tool Speed": "",
    "Pickaxe Power": "",
    "Hammer Power": "",
    "Axe Power": "",
    "Fishing Power": "",
    "Recipes": []
  },
  {
    "Item ID": "4442",
    "Name": "Scarab Fishing Rod",
    "Rarity": "1",
    "Use Time": "8 (Insanely fast)",
    "Velocity": "15",
    "Tool Speed": "",
    "Pickaxe Power": "",
    "Hammer Power": "",
    "Axe Power": "",
    "Fishing Power": "30%",
    "Recipes": []
  },
  {
    "Item ID": "4460",
    "Name": "Sandcastle Bucket",
    "Rarity": "1",
    "Use Time": "15 (Very fast)",
    "Velocity": "",
    "Tool Speed": "",
    "Pickaxe Power": "",
    "Hammer Power": "",
    "Axe Power": "",
    "Fishing Power": "",
    "Recipes": []
  },
  {
    "Item ID": "4587",
    "Name": "Worn Golf Club (Iron)",
    "Rarity": "",
    "Use Time": "12 (Very fast)",
    "Velocity": "",
    "Tool Speed": "",
    "Pickaxe Power": "",
    "Hammer Power": "",
    "Axe Power": "",
    "Fishing Power": "",
    "Recipes": []
  },
  {
    "Item ID": "4588",
    "Name": "Worn Golf Club (Putter)",
    "Rarity": "",
    "Use Time": "12 (Very fast)",
    "Velocity": "",
    "Tool Speed": "",
    "Pickaxe Power": "",
    "Hammer Power": "",
    "Axe Power": "",
    "Fishing Power": "",
    "Recipes": []
  },
  {
    "Item ID": "4589",
    "Name": "Worn Golf Club (Wedge)",
    "Rarity": "",
    "Use Time": "12 (Very fast)",
    "Velocity": "",
    "Tool Speed": "",
    "Pickaxe Power": "",
    "Hammer Power": "",
    "Axe Power": "",
    "Fishing Power": "",
    "Recipes": []
  },
  {
    "Item ID": "4590",
    "Name": "Worn Golf Club (Driver)",
    "Rarity": "",
    "Use Time": "12 (Very fast)",
    "Velocity": "",
    "Tool Speed": "",
    "Pickaxe Power": "",
    "Hammer Power": "",
    "Axe Power": "",
    "Fishing Power": "",
    "Recipes": []
  },
  {
    "Item ID": "4591",
    "Name": "Fancy Golf Club (Iron)",
    "Rarity": "",
    "Use Time": "12 (Very fast)",
    "Velocity": "",
    "Tool Speed": "",
    "Pickaxe Power": "",
    "Hammer Power": "",
    "Axe Power": "",
    "Fishing Power": "",
    "Recipes": []
  },
  {
    "Item ID": "4592",
    "Name": "Fancy Golf Club (Putter)",
    "Rarity": "",
    "Use Time": "12 (Very fast)",
    "Velocity": "",
    "Tool Speed": "",
    "Pickaxe Power": "",
    "Hammer Power": "",
    "Axe Power": "",
    "Fishing Power": "",
    "Recipes": []
  },
  {
    "Item ID": "4593",
    "Name": "Fancy Golf Club (Wedge)",
    "Rarity": "",
    "Use Time": "12 (Very fast)",
    "Velocity": "",
    "Tool Speed": "",
    "Pickaxe Power": "",
    "Hammer Power": "",
    "Axe Power": "",
    "Fishing Power": "",
    "Recipes": []
  },
  {
    "Item ID": "4594",
    "Name": "Fancy Golf Club (Driver)",
    "Rarity": "",
    "Use Time": "12 (Very fast)",
    "Velocity": "",
    "Tool Speed": "",
    "Pickaxe Power": "",
    "Hammer Power": "",
    "Axe Power": "",
    "Fishing Power": "",
    "Recipes": []
  },
  {
    "Item ID": "4595",
    "Name": "Premium Golf Club (Iron)",
    "Rarity": "",
    "Use Time": "12 (Very fast)",
    "Velocity": "",
    "Tool Speed": "",
    "Pickaxe Power": "",
    "Hammer Power": "",
    "Axe Power": "",
    "Fishing Power": "",
    "Recipes": []
  },
  {
    "Item ID": "4596",
    "Name": "Premium Golf Club (Putter)",
    "Rarity": "",
    "Use Time": "12 (Very fast)",
    "Velocity": "",
    "Tool Speed": "",
    "Pickaxe Power": "",
    "Hammer Power": "",
    "Axe Power": "",
    "Fishing Power": "",
    "Recipes": []
  },
  {
    "Item ID": "4597",
    "Name": "Premium Golf Club (Wedge)",
    "Rarity": "",
    "Use Time": "12 (Very fast)",
    "Velocity": "",
    "Tool Speed": "",
    "Pickaxe Power": "",
    "Hammer Power": "",
    "Axe Power": "",
    "Fishing Power": "",
    "Recipes": []
  },
  {
    "Item ID": "4598",
    "Name": "Premium Golf Club (Driver)",
    "Rarity": "",
    "Use Time": "12 (Very fast)",
    "Velocity": "",
    "Tool Speed": "",
    "Pickaxe Power": "",
    "Hammer Power": "",
    "Axe Power": "",
    "Fishing Power": "",
    "Recipes": []
  },
  {
    "Item ID": "4767",
    "Name": "Guide To Critter Companionship",
    "Rarity": "1",
    "Use Time": "",
    "Velocity": "",
    "Tool Speed": "",
    "Pickaxe Power": "",
    "Hammer Power": "",
    "Axe Power": "",
    "Fishing Power": "",
    "Recipes": []
  },
  {
    "Item ID": "4819",
    "Name": "Demon Conch",
    "Rarity": "4",
    "Use Time": "90 (Snail)",
    "Velocity": "",
    "Tool Speed": "",
    "Pickaxe Power": "",
    "Hammer Power": "",
    "Axe Power": "",
    "Fishing Power": "",
    "Recipes": []
  },
  {
    "Item ID": "4820",
    "Name": "Bottomless Lava Bucket",
    "Rarity": "7",
    "Use Time": "12 (Very fast)",
    "Velocity": "",
    "Tool Speed": "",
    "Pickaxe Power": "",
    "Hammer Power": "",
    "Axe Power": "",
    "Fishing Power": "",
    "Recipes": []
  },
  {
    "Item ID": "4821",
    "Name": "Lavaproof Bug Net",
    "Rarity": "3",
    "Use Time": "21 (Fast)",
    "Velocity": "",
    "Tool Speed": "",
    "Pickaxe Power": "",
    "Hammer Power": "",
    "Axe Power": "",
    "Fishing Power": "",
    "Recipes": []
  },
  {
    "Item ID": "4872",
    "Name": "Lava Absorbant Sponge",
    "Rarity": "7",
    "Use Time": "12 (Very fast)",
    "Velocity": "",
    "Tool Speed": "",
    "Pickaxe Power": "",
    "Hammer Power": "",
    "Axe Power": "",
    "Fishing Power": "",
    "Recipes": []
  }
]